RobotAxeLibrary/RobotAxeLibrary.py
RobotAxeLibrary/__init__.py
RobotAxeLibrary/version.py
robot_axelibrary-0.1.8.dist-info/LICENSE
robot_axelibrary-0.1.8.dist-info/METADATA
robot_axelibrary-0.1.8.dist-info/WHEEL
robot_axelibrary-0.1.8.dist-info/top_level.txt
robot_axelibrary-0.1.8.dist-info/RECORD
