Metadata-Version: 2.1
Name: robot-axelibrary
Version: 0.1.8
Summary: Robot Framework Library wrapper axe-selenium-python
Home-page: https://github.com/CaiqueCoelho/robot-axe-library
Author: Caique Coelho
Author-email: caiquedpfc@gmail.com
License: MIT
Keywords: robotframework testing automation axe selenium python
Platform: any
Classifier: License :: OSI Approved :: MIT License
Classifier: Programming Language :: Python
Classifier: Programming Language :: Python :: 2
Classifier: Programming Language :: Python :: 2.7
Classifier: Programming Language :: Python :: 3
Classifier: Programming Language :: Python :: 3.6
Classifier: Programming Language :: Python :: 3.7
Classifier: Programming Language :: Python :: 3.8
Classifier: Topic :: Software Development :: Testing
License-File: LICENSE
Requires-Dist: robotframework
Requires-Dist: axe-selenium-python
